clddp/__init__.py
clddp/dataloader.py
clddp/distill.py
clddp/dm.py
clddp/evaluation.py
clddp/mine.py
clddp/reranker.py
clddp/retriever.py
clddp/search.py
clddp/train.py
clddp/train_reranker.py
clddp/utils.py
clddp/args/__init__.py
clddp/args/base.py
clddp/args/distill.py
clddp/args/evaluation.py
clddp/args/mine.py
clddp/args/search.py
clddp/args/train.py
clddp/args/train_reranker.py
clddp-0.0.8.dist-info/METADATA
clddp-0.0.8.dist-info/WHEEL
clddp-0.0.8.dist-info/top_level.txt
clddp-0.0.8.dist-info/RECORD
