Metadata-Version: 2.1
Name: clddp
Version: 0.0.8
Summary: A package for training and doing inference with contrastive learning with multiple GPUs (Pytorch-DDP).
Home-page: https://https://github.com/kwang2049/ddp-cl
Author: Kexin Wang
Author-email: kexin.wang.2049@gmail.com
Project-URL: Bug Tracker, https://github.com/kwang2049/ddp-cl/issues
Classifier: Programming Language :: Python :: 3
Classifier: License :: OSI Approved :: Apache Software License
Classifier: Operating System :: OS Independent
Requires-Python: >=3.8
Requires-Dist: ujson
Requires-Dist: wandb
Requires-Dist: datasets
Requires-Dist: more-itertools
Requires-Dist: pytrec-eval
Requires-Dist: sentence-transformers
Requires-Dist: accelerate
Requires-Dist: faiss-cpu
